{
    "Process id": 1815386,
    "Process Name": "python3",
    "Affinity mask": [
        1,
        2,
        3,
        4,
        5,
        6,
        7
    ],
    "Execution time [seconds]": 68.76000000024214,
    "Process Exit status": 0,
    "CPU usage [% average] per second": [
        78.88888888684802,
        69.26829268135339,
        61.73913043353263,
        55.631733594718156,
        50.66904549526205,
        46.40522875732251,
        42.90030211407938,
        39.859649122807014,
        37.22149410163742,
        34.910878918214486,
        32.88940359000506,
        31.877729257933616,
        33.74677002567737,
        35.51080550120973,
        36.38914873732772,
        37.957181088440144,
        38.514090521044814,
        40.040899795195976,
        41.09105180536756,
        41.861341371455936,
        42.374727668788,
        43.29246935229645,
        43.91480730212062,
        44.52435436438819,
        45.0632911391077,
        45.554874310083044,
        46.17900683928519,
        46.28934449913871,
        47.26507713897341,
        47.35406437514849,
        48.19915254206379,
        48.27230531227154,
        48.88162854984114,
        49.04411764728273,
        49.749223787782185,
        50.011657728922344,
        50.512411751138075,
        50.779162956451096,
        51.043932144431295,
        51.04299702002876,
        51.354731137994094,
        51.37726994465536,
        51.6586730615123,
        51.90047021939785,
        52.074529389110445,
        52.052730696707194,
        52.51386321617577,
        52.54575104190861,
        52.90977042183586,
        53.1353711790393,
        53.59656652360515,
        53.56962025316455,
        53.93295718531266,
        53.90892769706211,
        54.127263984499805,
        54.40921280947951,
        54.35626650089941,
        54.418960244725824,
        54.46508840257456,
        54.79634002341693,
        54.8865619544315
    ],
    "Memory usage [MiB] per second": [
        {
            "Rss": 123.22265625,
            "Pss": 99.9541015625,
            "Private_Clean": 18.359375,
            "Private_Dirty": 77.9296875,
            "Uss": 96.2890625
        },
        {
            "Rss": 246.4453125,
            "Pss": 199.865234375,
            "Private_Clean": 36.6328125,
            "Private_Dirty": 155.859375,
            "Uss": 192.4921875
        },
        {
            "Rss": 369.66796875,
            "Pss": 299.666015625,
            "Private_Clean": 54.78125,
            "Private_Dirty": 233.7890625,
            "Uss": 288.5703125
        },
        {
            "Rss": 492.890625,
            "Pss": 399.458984375,
            "Private_Clean": 72.9296875,
            "Private_Dirty": 311.71875,
            "Uss": 384.6484375
        },
        {
            "Rss": 616.11328125,
            "Pss": 499.251953125,
            "Private_Clean": 91.078125,
            "Private_Dirty": 389.6484375,
            "Uss": 480.7265625
        },
        {
            "Rss": 739.3359375,
            "Pss": 599.044921875,
            "Private_Clean": 109.2265625,
            "Private_Dirty": 467.578125,
            "Uss": 576.8046875
        },
        {
            "Rss": 862.55859375,
            "Pss": 698.837890625,
            "Private_Clean": 127.375,
            "Private_Dirty": 545.5078125,
            "Uss": 672.8828125
        },
        {
            "Rss": 985.78125,
            "Pss": 798.630859375,
            "Private_Clean": 145.5234375,
            "Private_Dirty": 623.4375,
            "Uss": 768.9609375
        },
        {
            "Rss": 1109.00390625,
            "Pss": 898.423828125,
            "Private_Clean": 163.671875,
            "Private_Dirty": 701.3671875,
            "Uss": 865.0390625
        },
        {
            "Rss": 1232.2265625,
            "Pss": 998.20703125,
            "Private_Clean": 181.8203125,
            "Private_Dirty": 779.296875,
            "Uss": 961.1171875
        },
        {
            "Rss": 1355.515625,
            "Pss": 1098.0322265625,
            "Private_Clean": 200.0,
            "Private_Dirty": 857.23046875,
            "Uss": 1057.23046875
        },
        {
            "Rss": 1478.8671875,
            "Pss": 1197.9169921875,
            "Private_Clean": 218.2421875,
            "Private_Dirty": 935.1640625,
            "Uss": 1153.40625
        },
        {
            "Rss": 1602.21875,
            "Pss": 1297.8017578125,
            "Private_Clean": 236.484375,
            "Private_Dirty": 1013.09765625,
            "Uss": 1249.58203125
        },
        {
            "Rss": 1725.5703125,
            "Pss": 1397.6865234375,
            "Private_Clean": 254.7265625,
            "Private_Dirty": 1091.03125,
            "Uss": 1345.7578125
        },
        {
            "Rss": 1848.921875,
            "Pss": 1497.5712890625,
            "Private_Clean": 272.96875,
            "Private_Dirty": 1168.96484375,
            "Uss": 1441.93359375
        },
        {
            "Rss": 1972.2734375,
            "Pss": 1597.4560546875,
            "Private_Clean": 291.2109375,
            "Private_Dirty": 1246.8984375,
            "Uss": 1538.109375
        },
        {
            "Rss": 2095.625,
            "Pss": 1697.3408203125,
            "Private_Clean": 309.453125,
            "Private_Dirty": 1324.83203125,
            "Uss": 1634.28515625
        },
        {
            "Rss": 2218.9765625,
            "Pss": 1797.2255859375,
            "Private_Clean": 327.6953125,
            "Private_Dirty": 1402.765625,
            "Uss": 1730.4609375
        },
        {
            "Rss": 2342.328125,
            "Pss": 1897.1103515625,
            "Private_Clean": 345.9375,
            "Private_Dirty": 1480.69921875,
            "Uss": 1826.63671875
        },
        {
            "Rss": 2465.6796875,
            "Pss": 1996.9951171875,
            "Private_Clean": 364.1796875,
            "Private_Dirty": 1558.6328125,
            "Uss": 1922.8125
        },
        {
            "Rss": 2589.03125,
            "Pss": 2096.8798828125,
            "Private_Clean": 382.421875,
            "Private_Dirty": 1636.56640625,
            "Uss": 2018.98828125
        },
        {
            "Rss": 2712.3828125,
            "Pss": 2196.7646484375,
            "Private_Clean": 400.6640625,
            "Private_Dirty": 1714.5,
            "Uss": 2115.1640625
        },
        {
            "Rss": 2835.734375,
            "Pss": 2296.6494140625,
            "Private_Clean": 418.90625,
            "Private_Dirty": 1792.43359375,
            "Uss": 2211.33984375
        },
        {
            "Rss": 2959.0859375,
            "Pss": 2396.5341796875,
            "Private_Clean": 437.1484375,
            "Private_Dirty": 1870.3671875,
            "Uss": 2307.515625
        },
        {
            "Rss": 3082.44140625,
            "Pss": 2496.4228515625,
            "Private_Clean": 455.390625,
            "Private_Dirty": 1948.3046875,
            "Uss": 2403.6953125
        },
        {
            "Rss": 3205.8046875,
            "Pss": 2596.3193359375,
            "Private_Clean": 473.6328125,
            "Private_Dirty": 2026.25,
            "Uss": 2499.8828125
        },
        {
            "Rss": 3329.1796875,
            "Pss": 2696.2275390625,
            "Private_Clean": 491.875,
            "Private_Dirty": 2104.20703125,
            "Uss": 2596.08203125
        },
        {
            "Rss": 3452.5546875,
            "Pss": 2796.1357421875,
            "Private_Clean": 510.1171875,
            "Private_Dirty": 2182.1640625,
            "Uss": 2692.28125
        },
        {
            "Rss": 3575.9453125,
            "Pss": 2896.0595703125,
            "Private_Clean": 528.359375,
            "Private_Dirty": 2260.13671875,
            "Uss": 2788.49609375
        },
        {
            "Rss": 3699.35546875,
            "Pss": 2996.0029296875,
            "Private_Clean": 546.6015625,
            "Private_Dirty": 2338.12890625,
            "Uss": 2884.73046875
        },
        {
            "Rss": 3822.78125,
            "Pss": 3095.9619140625,
            "Private_Clean": 564.84375,
            "Private_Dirty": 2416.13671875,
            "Uss": 2980.98046875
        },
        {
            "Rss": 3946.20703125,
            "Pss": 3195.9208984375,
            "Private_Clean": 583.0859375,
            "Private_Dirty": 2494.14453125,
            "Uss": 3077.23046875
        },
        {
            "Rss": 4069.65625,
            "Pss": 3295.9033203125,
            "Private_Clean": 601.328125,
            "Private_Dirty": 2572.17578125,
            "Uss": 3173.50390625
        },
        {
            "Rss": 4193.125,
            "Pss": 3395.9052734375,
            "Private_Clean": 619.5703125,
            "Private_Dirty": 2650.2265625,
            "Uss": 3269.796875
        },
        {
            "Rss": 4316.6171875,
            "Pss": 3495.9306640625,
            "Private_Clean": 637.8125,
            "Private_Dirty": 2728.30078125,
            "Uss": 3366.11328125
        },
        {
            "Rss": 4440.1328125,
            "Pss": 3595.9794921875,
            "Private_Clean": 656.0546875,
            "Private_Dirty": 2806.3984375,
            "Uss": 3462.453125
        },
        {
            "Rss": 4563.68359375,
            "Pss": 3696.0634765625,
            "Private_Clean": 674.296875,
            "Private_Dirty": 2884.53125,
            "Uss": 3558.828125
        },
        {
            "Rss": 4687.234375,
            "Pss": 3796.1474609375,
            "Private_Clean": 692.5390625,
            "Private_Dirty": 2962.6640625,
            "Uss": 3655.203125
        },
        {
            "Rss": 4810.81640625,
            "Pss": 3896.2626953125,
            "Private_Clean": 710.78125,
            "Private_Dirty": 3040.828125,
            "Uss": 3751.609375
        },
        {
            "Rss": 4934.44140625,
            "Pss": 3996.4208984375,
            "Private_Clean": 729.0234375,
            "Private_Dirty": 3119.03515625,
            "Uss": 3848.05859375
        },
        {
            "Rss": 5058.09375,
            "Pss": 4096.6064453125,
            "Private_Clean": 747.265625,
            "Private_Dirty": 3197.26953125,
            "Uss": 3944.53515625
        },
        {
            "Rss": 5181.765625,
            "Pss": 4196.8115234375,
            "Private_Clean": 765.5078125,
            "Private_Dirty": 3275.5234375,
            "Uss": 4041.03125
        },
        {
            "Rss": 5309.19921875,
            "Pss": 4306.5595703125,
            "Private_Clean": 784.79296875,
            "Private_Dirty": 3356.4765625,
            "Uss": 4141.26953125
        }
    ],
    "Underlying Platform Basic Details": {
        "system network name": "ubuntu-focal",
        "processor name": "x86_64",
        "number of cores": 8,
        "machine type": "x86_64",
        "architectural detail": [
            "64bit",
            "ELF"
        ],
        "OS Name": "Linux",
        "OS release": "5.4.0-96-generic",
        "OS Version": "#109-Ubuntu SMP Wed Jan 12 16:49:16 UTC 2022",
        "Linux Kernel Version": "Linux-5.4.0-96-generic-x86_64-with-glibc2.29",
        "Python version": "3.8.10",
        "Python Build info": [
            "default",
            "Nov 26 2021 20:14:08"
        ],
        "Compiler info": "GCC 9.3.0",
        "Implementation": "CPython"
    },
    "CPU detailed information": {
        "processor-0": {
            "processor": "0",
            "vendor_id": "GenuineIntel",
            "cpu family": "6",
            "model": "78",
            "model name": "Intel(R) Core(TM) i7-6500U CPU @ 2.50GHz",
            "stepping": "3",
            "cpu MHz": "2591.986",
            "cache size": "4096 KB",
            "physical id": "0",
            "siblings": "8",
            "core id": "0",
            "cpu cores": "8",
            "apicid": "0",
            "initial apicid": "0",
            "fpu": "yes",
            "fpu_exception": "yes",
            "cpuid level": "22",
            "wp": "yes",
            "flags": "fpu vme de pse tsc msr pae mce cx8 apic sep mtrr pge mca cmov pat pse36 clflush mmx fxsr sse sse2 ht syscall nx rdtscp lm constant_tsc rep_good nopl xtopology nonstop_tsc cpuid tsc_known_freq pni pclmulqdq ssse3 cx16 pcid sse4_1 sse4_2 x2apic movbe popcnt aes xsave avx rdrand hypervisor lahf_lm abm 3dnowprefetch invpcid_single pti fsgsbase avx2 invpcid rdseed clflushopt md_clear flush_l1d",
            "bugs": "cpu_meltdown spectre_v1 spectre_v2 spec_store_bypass l1tf mds swapgs itlb_multihit srbds",
            "bogomips": "5183.97",
            "clflush size": "64",
            "cache_alignment": "64",
            "address sizes": "39 bits physical, 48 bits virtual",
            "power management": ""
        },
        "processor-1": {
            "processor": "1",
            "vendor_id": "GenuineIntel",
            "cpu family": "6",
            "model": "78",
            "model name": "Intel(R) Core(TM) i7-6500U CPU @ 2.50GHz",
            "stepping": "3",
            "cpu MHz": "2591.986",
            "cache size": "4096 KB",
            "physical id": "0",
            "siblings": "8",
            "core id": "1",
            "cpu cores": "8",
            "apicid": "1",
            "initial apicid": "1",
            "fpu": "yes",
            "fpu_exception": "yes",
            "cpuid level": "22",
            "wp": "yes",
            "flags": "fpu vme de pse tsc msr pae mce cx8 apic sep mtrr pge mca cmov pat pse36 clflush mmx fxsr sse sse2 ht syscall nx rdtscp lm constant_tsc rep_good nopl xtopology nonstop_tsc cpuid tsc_known_freq pni pclmulqdq ssse3 cx16 pcid sse4_1 sse4_2 x2apic movbe popcnt aes xsave avx rdrand hypervisor lahf_lm abm 3dnowprefetch invpcid_single pti fsgsbase avx2 invpcid rdseed clflushopt md_clear flush_l1d",
            "bugs": "cpu_meltdown spectre_v1 spectre_v2 spec_store_bypass l1tf mds swapgs itlb_multihit srbds",
            "bogomips": "5183.97",
            "clflush size": "64",
            "cache_alignment": "64",
            "address sizes": "39 bits physical, 48 bits virtual",
            "power management": ""
        },
        "processor-2": {
            "processor": "2",
            "vendor_id": "GenuineIntel",
            "cpu family": "6",
            "model": "78",
            "model name": "Intel(R) Core(TM) i7-6500U CPU @ 2.50GHz",
            "stepping": "3",
            "cpu MHz": "2591.986",
            "cache size": "4096 KB",
            "physical id": "0",
            "siblings": "8",
            "core id": "2",
            "cpu cores": "8",
            "apicid": "2",
            "initial apicid": "2",
            "fpu": "yes",
            "fpu_exception": "yes",
            "cpuid level": "22",
            "wp": "yes",
            "flags": "fpu vme de pse tsc msr pae mce cx8 apic sep mtrr pge mca cmov pat pse36 clflush mmx fxsr sse sse2 ht syscall nx rdtscp lm constant_tsc rep_good nopl xtopology nonstop_tsc cpuid tsc_known_freq pni pclmulqdq ssse3 cx16 pcid sse4_1 sse4_2 x2apic movbe popcnt aes xsave avx rdrand hypervisor lahf_lm abm 3dnowprefetch invpcid_single pti fsgsbase avx2 invpcid rdseed clflushopt md_clear flush_l1d",
            "bugs": "cpu_meltdown spectre_v1 spectre_v2 spec_store_bypass l1tf mds swapgs itlb_multihit srbds",
            "bogomips": "5183.97",
            "clflush size": "64",
            "cache_alignment": "64",
            "address sizes": "39 bits physical, 48 bits virtual",
            "power management": ""
        },
        "processor-3": {
            "processor": "3",
            "vendor_id": "GenuineIntel",
            "cpu family": "6",
            "model": "78",
            "model name": "Intel(R) Core(TM) i7-6500U CPU @ 2.50GHz",
            "stepping": "3",
            "cpu MHz": "2591.986",
            "cache size": "4096 KB",
            "physical id": "0",
            "siblings": "8",
            "core id": "3",
            "cpu cores": "8",
            "apicid": "3",
            "initial apicid": "3",
            "fpu": "yes",
            "fpu_exception": "yes",
            "cpuid level": "22",
            "wp": "yes",
            "flags": "fpu vme de pse tsc msr pae mce cx8 apic sep mtrr pge mca cmov pat pse36 clflush mmx fxsr sse sse2 ht syscall nx rdtscp lm constant_tsc rep_good nopl xtopology nonstop_tsc cpuid tsc_known_freq pni pclmulqdq ssse3 cx16 pcid sse4_1 sse4_2 x2apic movbe popcnt aes xsave avx rdrand hypervisor lahf_lm abm 3dnowprefetch invpcid_single pti fsgsbase avx2 invpcid rdseed clflushopt md_clear flush_l1d",
            "bugs": "cpu_meltdown spectre_v1 spectre_v2 spec_store_bypass l1tf mds swapgs itlb_multihit srbds",
            "bogomips": "5183.97",
            "clflush size": "64",
            "cache_alignment": "64",
            "address sizes": "39 bits physical, 48 bits virtual",
            "power management": ""
        },
        "processor-4": {
            "processor": "4",
            "vendor_id": "GenuineIntel",
            "cpu family": "6",
            "model": "78",
            "model name": "Intel(R) Core(TM) i7-6500U CPU @ 2.50GHz",
            "stepping": "3",
            "cpu MHz": "2591.986",
            "cache size": "4096 KB",
            "physical id": "0",
            "siblings": "8",
            "core id": "4",
            "cpu cores": "8",
            "apicid": "4",
            "initial apicid": "4",
            "fpu": "yes",
            "fpu_exception": "yes",
            "cpuid level": "22",
            "wp": "yes",
            "flags": "fpu vme de pse tsc msr pae mce cx8 apic sep mtrr pge mca cmov pat pse36 clflush mmx fxsr sse sse2 ht syscall nx rdtscp lm constant_tsc rep_good nopl xtopology nonstop_tsc cpuid tsc_known_freq pni pclmulqdq ssse3 cx16 pcid sse4_1 sse4_2 x2apic movbe popcnt aes xsave avx rdrand hypervisor lahf_lm abm 3dnowprefetch invpcid_single pti fsgsbase avx2 invpcid rdseed clflushopt md_clear flush_l1d",
            "bugs": "cpu_meltdown spectre_v1 spectre_v2 spec_store_bypass l1tf mds swapgs itlb_multihit srbds",
            "bogomips": "5183.97",
            "clflush size": "64",
            "cache_alignment": "64",
            "address sizes": "39 bits physical, 48 bits virtual",
            "power management": ""
        },
        "processor-5": {
            "processor": "5",
            "vendor_id": "GenuineIntel",
            "cpu family": "6",
            "model": "78",
            "model name": "Intel(R) Core(TM) i7-6500U CPU @ 2.50GHz",
            "stepping": "3",
            "cpu MHz": "2591.986",
            "cache size": "4096 KB",
            "physical id": "0",
            "siblings": "8",
            "core id": "5",
            "cpu cores": "8",
            "apicid": "5",
            "initial apicid": "5",
            "fpu": "yes",
            "fpu_exception": "yes",
            "cpuid level": "22",
            "wp": "yes",
            "flags": "fpu vme de pse tsc msr pae mce cx8 apic sep mtrr pge mca cmov pat pse36 clflush mmx fxsr sse sse2 ht syscall nx rdtscp lm constant_tsc rep_good nopl xtopology nonstop_tsc cpuid tsc_known_freq pni pclmulqdq ssse3 cx16 pcid sse4_1 sse4_2 x2apic movbe popcnt aes xsave avx rdrand hypervisor lahf_lm abm 3dnowprefetch invpcid_single pti fsgsbase avx2 invpcid rdseed clflushopt md_clear flush_l1d",
            "bugs": "cpu_meltdown spectre_v1 spectre_v2 spec_store_bypass l1tf mds swapgs itlb_multihit srbds",
            "bogomips": "5183.97",
            "clflush size": "64",
            "cache_alignment": "64",
            "address sizes": "39 bits physical, 48 bits virtual",
            "power management": ""
        },
        "processor-6": {
            "processor": "6",
            "vendor_id": "GenuineIntel",
            "cpu family": "6",
            "model": "78",
            "model name": "Intel(R) Core(TM) i7-6500U CPU @ 2.50GHz",
            "stepping": "3",
            "cpu MHz": "2591.986",
            "cache size": "4096 KB",
            "physical id": "0",
            "siblings": "8",
            "core id": "6",
            "cpu cores": "8",
            "apicid": "6",
            "initial apicid": "6",
            "fpu": "yes",
            "fpu_exception": "yes",
            "cpuid level": "22",
            "wp": "yes",
            "flags": "fpu vme de pse tsc msr pae mce cx8 apic sep mtrr pge mca cmov pat pse36 clflush mmx fxsr sse sse2 ht syscall nx rdtscp lm constant_tsc rep_good nopl xtopology nonstop_tsc cpuid tsc_known_freq pni pclmulqdq ssse3 cx16 pcid sse4_1 sse4_2 x2apic movbe popcnt aes xsave avx rdrand hypervisor lahf_lm abm 3dnowprefetch invpcid_single pti fsgsbase avx2 invpcid rdseed clflushopt md_clear flush_l1d",
            "bugs": "cpu_meltdown spectre_v1 spectre_v2 spec_store_bypass l1tf mds swapgs itlb_multihit srbds",
            "bogomips": "5183.97",
            "clflush size": "64",
            "cache_alignment": "64",
            "address sizes": "39 bits physical, 48 bits virtual",
            "power management": ""
        },
        "processor-7": {
            "processor": "7",
            "vendor_id": "GenuineIntel",
            "cpu family": "6",
            "model": "78",
            "model name": "Intel(R) Core(TM) i7-6500U CPU @ 2.50GHz",
            "stepping": "3",
            "cpu MHz": "2591.986",
            "cache size": "4096 KB",
            "physical id": "0",
            "siblings": "8",
            "core id": "7",
            "cpu cores": "8",
            "apicid": "7",
            "initial apicid": "7",
            "fpu": "yes",
            "fpu_exception": "yes",
            "cpuid level": "22",
            "wp": "yes",
            "flags": "fpu vme de pse tsc msr pae mce cx8 apic sep mtrr pge mca cmov pat pse36 clflush mmx fxsr sse sse2 ht syscall nx rdtscp lm constant_tsc rep_good nopl xtopology nonstop_tsc cpuid tsc_known_freq pni pclmulqdq ssse3 cx16 pcid sse4_1 sse4_2 x2apic movbe popcnt aes xsave avx rdrand hypervisor lahf_lm abm 3dnowprefetch invpcid_single pti fsgsbase avx2 invpcid rdseed clflushopt md_clear flush_l1d",
            "bugs": "cpu_meltdown spectre_v1 spectre_v2 spec_store_bypass l1tf mds swapgs itlb_multihit srbds",
            "bogomips": "5183.97",
            "clflush size": "64",
            "cache_alignment": "64",
            "address sizes": "39 bits physical, 48 bits virtual",
            "power management": ""
        }
    }
}